LICENSE
MANIFEST.in
README.md
runfunc.py
setup.py
test.py
examples/basic.py
runfunc.egg-info/PKG-INFO
runfunc.egg-info/SOURCES.txt
runfunc.egg-info/dependency_links.txt
runfunc.egg-info/not-zip-safe
runfunc.egg-info/top_level.txt