Metadata-Version: 1.0
Name: runfunc
Version: 0.0.1
Summary: An alternative syntax for optparse
Home-page: http://github.com/davisp/runfunc
Author: Paul Joseph Davis
Author-email: paul.joseph.davis@gmail.com
License: BSD
Keywords: optparse command-line help
Platform: any
Classifier: Development Status :: 3 - Alpha
Classifier: Intended Audience :: Developers
Classifier: License :: OSI Approved :: BSD License
Classifier: Natural Language :: English
Classifier: Operating System :: OS Independent
Classifier: Programming Language :: Python
Classifier: Topic :: Software Development :: Libraries :: Python Modules
